Metadata-Version: 2.1
Name: django-react-jollof
Version: 1.0.1
Summary: A CLI tool to scaffold Django + React projects with options for social login and styling frameworks.
Home-page: https://github.com/sir-temi/django-react-jollof
Author: Temitope Kayode
Author-email: cwt@temilimited.com
License: MIT
Project-URL: Bug Tracker, https://github.com/sir-temi/django-react-jollof/issues
Project-URL: Documentation, https://github.com/sir-temi/django-react-jollof#readme
Project-URL: Source Code, https://github.com/sir-temi/django-react-jollof
Project-URL: Changelog, https://github.com/sir-temi/django-react-jollof/releases
Keywords: django react cli scaffolding jwt social-auth
Classifier: Development Status :: 4 - Beta
Classifier: Environment :: Console
Classifier: Framework :: Django
Classifier: Programming Language :: Python :: 3.10
Classifier: Programming Language :: Python :: 3.11
Classifier: License :: OSI Approved :: MIT License
Classifier: Operating System :: OS Independent
Classifier: Topic :: Software Development :: Build Tools
Classifier: Topic :: Software Development :: Libraries
Classifier: Topic :: Software Development :: Libraries :: Python Modules
Requires-Python: >=3.10
License-File: LICENSE
Requires-Dist: click>=8.0
Requires-Dist: requests>=2.0
Requires-Dist: python-decouple>=3.6
Requires-Dist: djangorestframework>=3.13
Requires-Dist: djangorestframework-simplejwt>=5.2
Requires-Dist: django-cors-headers>=3.13
Requires-Dist: django-allauth>=0.53
Provides-Extra: dev
Requires-Dist: flake8>=4.0; extra == "dev"
